jrpyoop/__init__.py
jrpyoop/__version__.py
jrpyoop/data/chess_games.zip
jrpyoop/data/movies.zip
jrpyoop/data.py
jrpyoop-0.4.0.dist-info/METADATA
jrpyoop-0.4.0.dist-info/WHEEL
jrpyoop-0.4.0.dist-info/RECORD
