Metadata-Version: 2.1
Name: jrpyoop
Version: 0.4.0
Summary: Jumping Rivers: Object-Oriented Programming in Python
Author: Russ Hyde
Author-email: russ@jumpingrivers.com
Requires-Python: >=3.9
Classifier: Programming Language :: Python :: 3
Classifier: Programming Language :: Python :: 3.9
Classifier: Programming Language :: Python :: 3.10
Classifier: Programming Language :: Python :: 3.11
Classifier: Programming Language :: Python :: 3.12
Requires-Dist: matplotlib (>=3.5,<4.0)
Requires-Dist: measurement (>=3.2,<4.0)
Requires-Dist: numpy (>=2.0.0,<3.0.0)
Requires-Dist: pandas (>=2.2.2,<3.0.0)
Requires-Dist: scikit-learn (>=1.3,<2.0)
